{
  "version": 1,
  "description": "StudyClawHub Skill Registry",
  "skills": [
    {
      "name": "sch-create",
      "repo": "https://github.com/Trust-App-AI-Lab/StudyClawHub",
      "path": "hub-skills/sch-create",
      "author": "EnyanDai",
      "registeredAt": "2026-04-12T00:00:00Z"
    },
    {
      "name": "sch-submit",
      "repo": "https://github.com/Trust-App-AI-Lab/StudyClawHub",
      "path": "hub-skills/sch-submit",
      "author": "EnyanDai",
      "registeredAt": "2026-04-12T00:00:00Z"
    },
    {
      "name": "sch-install",
      "repo": "https://github.com/Trust-App-AI-Lab/StudyClawHub",
      "path": "hub-skills/sch-install",
      "author": "EnyanDai",
      "registeredAt": "2026-04-12T00:00:00Z"
    }
  ]
}
